MANIFEST.in
README.rst
setup.cfg
setup.py
pyrelic/__init__.py
pyrelic/bi.py
pyrelic/bls.py
pyrelic/common.py
pyrelic/ec.py
pyrelic/ecqv.py
pyrelic/pbc.py
pyrelic/prf.py
pyrelic/profile.py
pyrelic/relic.py
pyrelic/testBigInt.py
pyrelic/testBls.py
pyrelic/testPbc.py
pyrelic/testPbcArith.py
pyrelic/testVpop.py
pyrelic/testVprf.py
pyrelic/testcommon.py
pyrelic/vpop.py
pyrelic/vpopProfile.py
pyrelic/vprf.py
pyrelic/lib/librelic.dylib
pyrelic/lib/librelic.so
pythia_pyrelic.egg-info/PKG-INFO
pythia_pyrelic.egg-info/SOURCES.txt
pythia_pyrelic.egg-info/dependency_links.txt
pythia_pyrelic.egg-info/not-zip-safe
pythia_pyrelic.egg-info/top_level.txt