Metadata-Version: 1.1
Name: pythia-pyrelic
Version: 1.0.1
Summary: pyrelic is a python module to interact with the RELIC cryptography library which performs high-performance elliptic curve cryptography and pairing-based elliptic curves. pyrelic also includes verifiable pseudorandom functions used in Pythia.
Home-page: https://github.com/ace0/pyrelic
Author: Adam Everspaugh
Author-email: ace@cs.wisc.edu
License: MIT
Keywords: encryption,elliptic curve cryptography,pairing based cryptography,oblvious pseudorandom function,partially oblivious pseudorandom function
Platform: UNKNOWN
Classifier: Development Status :: 4 - Beta
Classifier: Intended Audience :: Developers
Classifier: License :: OSI Approved :: MIT License
Classifier: Operating System :: MacOS
Classifier: Operating System :: MacOS :: MacOS X
Classifier: Operating System :: POSIX :: Linux
Classifier: Operating System :: Unix
Classifier: Programming Language :: Python :: 2
Classifier: Programming Language :: Python :: 2.7
Classifier: Topic :: Security
Classifier: Topic :: Security :: Cryptography
